<annotation>
	<folder>M4 IMAGES</folder>
	<filename>p3wjee0r20t11.jpg</filename>
	<path>D:\PRJ2\RealTimeObjectDetection\Tensorflow\workspace\images\M4 IMAGES\p3wjee0r20t11.jpg</path>
	<source>
		<database>Unknown</database>
	</source>
	<size>
		<width>2000</width>
		<height>1333</height>
		<depth>3</depth>
	</size>
	<segmented>0</segmented>
	<object>
		<name>m4_carbine</name>
		<pose>Unspecified</pose>
		<truncated>0</truncated>
		<difficult>0</difficult>
		<bndbox>
			<xmin>686</xmin>
			<ymin>480</ymin>
			<xmax>1497</xmax>
			<ymax>1278</ymax>
		</bndbox>
	</object>
</annotation>
